eazy_user/__init__.py
eazy_user/apps.py
eazy_user/models.py
eazy_user/migrations/0001_initial.py
eazy_user/migrations/__init__.py
eazy_django_user-1.1.1.dist-info/LICENSE
eazy_django_user-1.1.1.dist-info/METADATA
eazy_django_user-1.1.1.dist-info/WHEEL
eazy_django_user-1.1.1.dist-info/top_level.txt
eazy_django_user-1.1.1.dist-info/RECORD
