Metadata-Version: 2.1
Name: eazy-django-user
Version: 1.1.1
Summary: Custom User Model
Home-page: https://www.vice.codes
Author: Eazy
Author-email: codeepoch@gmail.com
Maintainer: Eazy
Maintainer-email: codeepoch@gmail.com
License: MTI License        
Keywords: django model
Classifier: Framework :: Django
Classifier: License :: OSI Approved :: MIT License
Classifier: Intended Audience :: Developers
Classifier: Operating System :: OS Independent
Classifier: Programming Language :: Python :: 3
Classifier: Programming Language :: Python :: 3 :: Only
Classifier: Programming Language :: Python :: 3.5
Classifier: Programming Language :: Python :: 3.6
Classifier: Programming Language :: Python :: 3.7
Classifier: Programming Language :: Python :: 3.8
Classifier: Topic :: Software Development :: Libraries :: Python Modules
License-File: LICENSE
